CHANGES
LICENSE
MANIFEST.in
README.rst
setup.cfg
setup.py
aiohttp_themes/__init__.py
aiohttp_themes/asset.py
aiohttp_themes/theme.py
aiohttp_themes.egg-info/PKG-INFO
aiohttp_themes.egg-info/SOURCES.txt
aiohttp_themes.egg-info/dependency_links.txt
aiohttp_themes.egg-info/not-zip-safe
aiohttp_themes.egg-info/requires.txt
aiohttp_themes.egg-info/top_level.txt