Metadata-Version: 1.1
Name: aiohttp_themes
Version: 0.0.2
Summary: Aiohttp Chat Example
Home-page: https://github.com/storborg/aiohttp_themes
Author: Scott Torborg
Author-email: storborg@gmail.com
License: MIT
Keywords: asyncio aiohttp frontend themes sass
Platform: UNKNOWN
Classifier: Development Status :: 2 - Pre-Alpha
Classifier: License :: OSI Approved :: MIT License
Classifier: Programming Language :: Python :: 3.5
